jupytercv/__init__.py
jupytercv/images.py
jupytercv-0.0.3.dev0.dist-info/METADATA
jupytercv-0.0.3.dev0.dist-info/RECORD
jupytercv-0.0.3.dev0.dist-info/WHEEL
jupytercv-0.0.3.dev0.dist-info/top_level.txt
