Metadata-Version: 2.1
Name: jupytercv
Version: 0.0.3.dev0
Summary: Computer vision utils for Jupyter notebook
Home-page: https://github.com/shygiants/jupytercv
Author: Sanghoon Yoon
Author-email: shygiants@gmail.com
License: UNKNOWN
Keywords: jupyter,notebook
Platform: UNKNOWN
